savescreen/__init__.py
savescreen/__main__.py
savescreen/screenshot.py
savescreen-1.0.0.dist-info/METADATA
savescreen-1.0.0.dist-info/WHEEL
savescreen-1.0.0.dist-info/entry_points.txt
savescreen-1.0.0.dist-info/top_level.txt
savescreen-1.0.0.dist-info/RECORD
